{"name":"VSUBAR-1 Verify selling USD by average rate","testSteps":[{"number":1,"description":"[1] {currencyName\u003dUSD, currencyAmount\u003d300.00, rateValue\u003dПриватБанк, currencyList\u003dUAH,EUR,RUB}","duration":21220,"startTime":1518043927388,"children":[{"number":2,"description":"Given User opens currency converter page","duration":9093,"startTime":1518043927414,"result":"SUCCESS","children":[{"number":3,"description":"User opens converter page","duration":8008,"startTime":1518043927497,"result":"SUCCESS"}]},{"number":4,"description":"When User clicks on sell option link","duration":1133,"startTime":1518043937508,"result":"SUCCESS","children":[{"number":5,"description":"User selects sell option","duration":132,"startTime":1518043937509,"result":"SUCCESS"}]},{"number":6,"description":"And User selects {USD} currency from dropdown list","duration":1131,"startTime":1518043939641,"result":"SUCCESS","children":[{"number":7,"description":"User selects currency from dropdown list: \u003cspan class\u003d\u0027step-parameter\u0027\u003eUSD\u003c/span\u003e","duration":118,"startTime":1518043939653,"result":"SUCCESS"}]},{"number":8,"description":"And User puts {300.00} value of currency amount in sum field","duration":1213,"startTime":1518043941773,"result":"SUCCESS","children":[{"number":9,"description":"User puts currency amount in sum field: \u003cspan class\u003d\u0027step-parameter\u0027\u003e300.0\u003c/span\u003e","duration":211,"startTime":1518043941775,"result":"SUCCESS"}]},{"number":10,"description":"And User selects {ПриватБанк} rate value from dropdown list","duration":1153,"startTime":1518043943987,"result":"SUCCESS","children":[{"number":11,"description":"User selects rate value from dropdown list: \u003cspan class\u003d\u0027step-parameter\u0027\u003eПриватБанк\u003c/span\u003e","duration":152,"startTime":1518043943988,"result":"SUCCESS"}]},{"number":12,"description":"Then User checks results for the list of currency {UAH,EUR,RUB}","duration":1462,"startTime":1518043946141,"result":"SUCCESS","children":[{"number":13,"description":"User checks result for currency list: \u003cspan class\u003d\u0027step-parameter\u0027\u003e[UAH, EUR, RUB]\u003c/span\u003e","duration":458,"startTime":1518043946143,"result":"SUCCESS"}]}]}],"userStory":{"id":"verify_selling_usd_by_average_rate","storyName":"Verify selling usd by average rate","path":"stories/verify_selling_usd_by_average_rate.story","narrative":"As a user\nI want to perform an action\nSo that I can achieve a business goal","type":"story"},"title":"VSUBAR-1 Verify selling USD by average rate","coreIssues":["VSUBAR-1"],"tags":[{"name":"Verify selling usd by average rate","type":"story"}],"startTime":1518043927253,"duration":21355,"driver":"chrome","dataTable":{"headers":["currencyName","currencyAmount","rateValue","currencyList"],"rows":[{"values":["USD","300.00","ПриватБанк","UAH,EUR,RUB"],"result":"SUCCESS"}],"predefinedRows":true,"currentRow":{"value":0},"dataSetDescriptors":[{"startRow":0,"rowCount":0}]},"manual":false,"result":"SUCCESS","issues":["VSUBAR-1"]}